{"title":"Happiness Is A Thing Called Joe","artist":"Harold Arlen","style":"Medium Swing","key":"C","chartData":[{"barData":["C^7","","D-7",""],"denominator":4,"numerator":4,"endBarline":"|","section":"i","startBarline":"["},{"barData":["E-7","","F^7",""],"endBarline":"|","startBarline":"|"},{"barData":["C^7","","D-7",""],"endBarline":"|","section":"i","annotations":[],"startBarline":"|"},{"barData":["E-7","","F^7",""],"endBarline":"|","startBarline":"|"},{"barData":["B-7","","E13",""],"endBarline":"|","startBarline":"|"},{"barData":["B-9","","E9#11",""],"endBarline":"|","startBarline":"|"},{"barData":["A-9","","D13",""],"endBarline":"|","startBarline":"|"},{"barData":["D-7","","",""],"endBarline":"|","startBarline":"|"},{"barData":["G13","","",""],"endBarline":"]","startBarline":"|"},{"barData":["C69","","D-7",""],"endBarline":"|","section":"A","startBarline":"["},{"barData":["C/E","","G9",""],"endBarline":"|","startBarline":"|"},{"barData":["C69","","G7sus",""],"endBarline":"|","startBarline":"|"},{"barData":["C69","","G7b9",""],"endBarline":"|","startBarline":"|"},{"barData":["C69","","D-7",""],"endBarline":"|","startBarline":"|"},{"barData":["C/E","","A7b9",""],"endBarline":"|","startBarline":"|"},{"barData":["G13","","",""],"endBarline":"|","startBarline":"|"},{"barData":["G13","","",""],"endBarline":"]","startBarline":"|"},{"barData":["G13","","Ab13#9",""],"endBarline":"|","section":"B","startBarline":"["},{"barData":["G13","","Ab13#9",""],"endBarline":"|","startBarline":"|"},{"barData":["G13","","",""],"endBarline":"|","startBarline":"|"},{"barData":["F9#11","","",""],"endBarline":"|","startBarline":"|"},{"barData":["E-9","","",""],"endBarline":"|","startBarline":"|"},{"barData":["A7#5","","",""],"endBarline":"|","startBarline":"|"},{"barData":["D-7","","",""],"endBarline":"|","startBarline":"|"},{"barData":["G13","","",""],"endBarline":"]","startBarline":"|"},{"barData":["C69","","D-7",""],"endBarline":"|","section":"A","startBarline":"["},{"barData":["C/E","","G9",""],"endBarline":"|","startBarline":"|"},{"barData":["C69","","G7sus",""],"endBarline":"|","startBarline":"|"},{"barData":["C69","","G7b9",""],"endBarline":"|","startBarline":"|"},{"barData":["C69","","D-7",""],"endBarline":"|","startBarline":"|"},{"barData":["Ebo7","","C7#5/E",""],"endBarline":"|","startBarline":"|"},{"barData":["F69","","C7#5",""],"endBarline":"|","startBarline":"|"},{"barData":["F69","","",""],"endBarline":"]","startBarline":"|"},{"barData":["F#-7b5","","",""],"endBarline":"|","section":"C","startBarline":"["},{"barData":["F-9","","",""],"endBarline":"|","startBarline":"|"},{"barData":["E-7","","",""],"endBarline":"|","startBarline":"|"},{"barData":["A9","","",""],"endBarline":"|","startBarline":"|"},{"barData":["D9","","Ab9",""],"endBarline":"|","startBarline":"|"},{"barData":["D-9","","G7b9",""],"endBarline":"|","startBarline":"|"},{"barData":["G-7","","",""],"endBarline":"|","startBarline":"|"},{"barData":["C7#5","","",""],"endBarline":"|","startBarline":"|"},{"barData":["F^7","","Ab9",""],"endBarline":"|","startBarline":"|"},{"barData":["D-9","","F-/G",""],"endBarline":"|","startBarline":"|"},{"barData":["C6","","",""],"endBarline":"|","startBarline":"|"},{"barData":["C6","","",""],"endBarline":"Z","startBarline":"|"}]}