{"title":"I'm Always Chasing Rainbows","artist":"Harry Carroll","style":"Medium Swing","key":"G","chartData":[{"barData":["G^7","","",""],"denominator":4,"numerator":4,"endBarline":"|","section":"A","startBarline":"["},{"barData":["/","/","C-6",""],"endBarline":"|","startBarline":"|"},{"barData":["G^7","","",""],"endBarline":"|","startBarline":"|"},{"barData":["G^7","","",""],"endBarline":"|","startBarline":"|"},{"barData":["F#o7","","G^7",""],"endBarline":"|","startBarline":"|"},{"barData":["C-6","","G^7",""],"endBarline":"|","startBarline":"|"},{"barData":["A-7","","",""],"endBarline":"|","startBarline":"|"},{"barData":["D7","","",""],"endBarline":"|","startBarline":"|"},{"barData":["E7","","",""],"endBarline":"|","startBarline":"|"},{"barData":["B-7b5","","E7",""],"endBarline":"|","startBarline":"|"},{"barData":["A-7","","E7",""],"endBarline":"|","startBarline":"|"},{"barData":["A-7","","",""],"endBarline":"|","startBarline":"|"},{"barData":["A7","","",""],"endBarline":"|","startBarline":"|"},{"barData":["A7","","",""],"endBarline":"|","startBarline":"|"},{"barData":["A-7/D","","",""],"endBarline":"|","startBarline":"|"},{"barData":["D7","","",""],"endBarline":"]","startBarline":"|"},{"barData":["G7","","",""],"endBarline":"|","section":"B","startBarline":"["},{"barData":["G7","","",""],"endBarline":"|","startBarline":"|"},{"barData":["C6","","",""],"endBarline":"|","startBarline":"|"},{"barData":["C6","","",""],"endBarline":"|","startBarline":"|"},{"barData":["E7","","",""],"endBarline":"|","startBarline":"|"},{"barData":["E7","","",""],"endBarline":"|","startBarline":"|"},{"barData":["A7","","",""],"endBarline":"|","startBarline":"|"},{"barData":["D7","","A-7","Ab7"],"endBarline":"|","startBarline":"|"},{"barData":["G^7","","",""],"endBarline":"|","startBarline":"|"},{"barData":["/","/","C-6",""],"endBarline":"|","startBarline":"|"},{"barData":["G^7","","",""],"endBarline":"|","startBarline":"|"},{"barData":["E7","","",""],"endBarline":"|","startBarline":"|"},{"barData":["A-7","","",""],"endBarline":"|","startBarline":"|"},{"barData":["D7","","D7b9",""],"endBarline":"|","startBarline":"|"},{"barData":["G6","","",""],"endBarline":"|","startBarline":"|"},{"barData":["A-7","","D7",""],"endBarline":"Z","startBarline":"|"}]}