{"title":"Let's Fall In Love","artist":"Harold Arlen","style":"Medium Swing","key":"C","chartData":[{"barData":["C6","","A-7",""],"denominator":4,"numerator":4,"endBarline":"|","section":"A","startBarline":"{"},{"barData":["D-7","","G7",""],"endBarline":"|","startBarline":"|"},{"barData":["C6","","A-7",""],"endBarline":"|","startBarline":"|"},{"barData":["D-7","","G7",""],"endBarline":"|","startBarline":"|"},{"barData":["E-7","","A-7",""],"endBarline":"|","startBarline":"|"},{"barData":["D-7","","G7",""],"endBarline":"|","startBarline":"|"},{"barData":["E7","","A7",""],"endBarline":"|","timeBar":"1","startBarline":"|"},{"barData":["D7","","G7",""],"endBarline":"}","startBarline":"|"},{"barData":["B-7b5","","E7",""],"endBarline":"|","timeBar":"2","startBarline":"|"},{"barData":["B-7b5","","E7",""],"endBarline":"]","startBarline":"|"},{"barData":["A-","","A-^7",""],"endBarline":"|","section":"B","startBarline":"["},{"barData":["A-7","","",""],"endBarline":"|","startBarline":"|"},{"barData":["D7","","A-7",""],"endBarline":"|","startBarline":"|"},{"barData":["D7","","D#o7",""],"endBarline":"|","startBarline":"|"},{"barData":["E-7","","A-7",""],"endBarline":"|","startBarline":"|"},{"barData":["D-7","","G7",""],"endBarline":"|","startBarline":"|"},{"barData":["E-7","","A7b9",""],"endBarline":"|","startBarline":"|"},{"barData":["D-7","","G7",""],"endBarline":"]","startBarline":"|"},{"barData":["C6","","A-7",""],"endBarline":"|","section":"A","startBarline":"["},{"barData":["D-7","","G7",""],"endBarline":"|","startBarline":"|"},{"barData":["C6","","A-7",""],"endBarline":"|","startBarline":"|"},{"barData":["D-7","","G7",""],"endBarline":"|","startBarline":"|"},{"barData":["E-7","","A-7",""],"endBarline":"|","startBarline":"|"},{"barData":["D-7","","G7",""],"endBarline":"|","startBarline":"|"},{"barData":["C6","","A-7",""],"endBarline":"|","startBarline":"|"},{"barData":["D-7","","G7",""],"endBarline":"Z","startBarline":"|"}]}