{"title":"People","artist":"Jule Styne","style":"Ballad","key":"Bb","chartData":[{"barData":["Bb^7","","G-7",""],"denominator":4,"numerator":4,"endBarline":"|","section":"A","startBarline":"["},{"barData":["C-7","","F7",""],"endBarline":"|","startBarline":"|"},{"barData":["Bb^7","","G-7",""],"endBarline":"|","startBarline":"|"},{"barData":["C-7","","F7b9",""],"endBarline":"|","startBarline":"|"},{"barData":["Eb/Bb","","",""],"endBarline":"|","startBarline":"|"},{"barData":["Bb^7","","",""],"endBarline":"|","startBarline":"|"},{"barData":["A-7","","",""],"endBarline":"|","startBarline":"|"},{"barData":["D7","","",""],"endBarline":"]","startBarline":"|"},{"barData":["G-^7","","",""],"endBarline":"|","section":"B","startBarline":"["},{"barData":["G-^7","","",""],"endBarline":"|","startBarline":"|"},{"barData":["C7#11","","",""],"endBarline":"|","startBarline":"|"},{"barData":["C7#11","","",""],"endBarline":"|","startBarline":"|"},{"barData":["G-7b5","","C7",""],"endBarline":"|","startBarline":"|"},{"barData":["F^7","","F6",""],"endBarline":"|","startBarline":"|"},{"barData":["G/B","","Bb-6",""],"endBarline":"|","startBarline":"|"},{"barData":["F/A","","Abo7",""],"endBarline":"|","startBarline":"|"},{"barData":["G-7","","",""],"endBarline":"|","startBarline":"|"},{"barData":["C7","","",""],"endBarline":"|","startBarline":"|"},{"barData":["E/F","F6","/","/"],"endBarline":"|","startBarline":"|"},{"barData":["C-7","","F7",""],"endBarline":"]","startBarline":"|"},{"barData":["Bb^7","","G-7",""],"endBarline":"|","section":"A","startBarline":"["},{"barData":["C-7","","F7",""],"endBarline":"|","startBarline":"|"},{"barData":["Bb^7","","G-7",""],"endBarline":"|","startBarline":"|"},{"barData":["C-7","","F7b9",""],"endBarline":"|","startBarline":"|"},{"barData":["Eb/Bb","","",""],"endBarline":"|","startBarline":"|"},{"barData":["Bb^7","","",""],"endBarline":"|","startBarline":"|"},{"barData":["F-7","","",""],"endBarline":"|","startBarline":"|"},{"barData":["Bb7","","",""],"endBarline":"]","startBarline":"|"},{"barData":["Eb^7","","",""],"endBarline":"|","section":"C","startBarline":"["},{"barData":["/","/","Eb-7",""],"endBarline":"|","startBarline":"|"},{"barData":["Bb6","","",""],"endBarline":"|","startBarline":"|"},{"barData":["F-7","","Bb7b9",""],"endBarline":"|","startBarline":"|"},{"barData":["Eb^7","","",""],"endBarline":"|","startBarline":"|"},{"barData":["/","/","F7/Eb",""],"endBarline":"|","startBarline":"|"},{"barData":["Bb/D","","",""],"endBarline":"|","startBarline":"|"},{"barData":["E-7b5","","A7",""],"endBarline":"|","startBarline":"|"},{"barData":["Bb/D","","G-7",""],"endBarline":"|","startBarline":"|"},{"barData":["C-7","","F7",""],"endBarline":"|","startBarline":"|"},{"barData":["Bb^7","","",""],"endBarline":"|","startBarline":"|"},{"barData":["/","/","F-7","Bb7"],"endBarline":"|","startBarline":"|"},{"barData":["Eb^7","","",""],"endBarline":"|","startBarline":"|"},{"barData":["Ab9#11","","",""],"endBarline":"|","startBarline":"|"},{"barData":["Eb/F","","",""],"endBarline":"|","startBarline":"|"},{"barData":["C-7","","C-7/F",""],"endBarline":"|","startBarline":"|"},{"barData":["Bb6","","",""],"endBarline":"|","startBarline":"|"},{"barData":["C-7","","F7",""],"endBarline":"Z","startBarline":"|"}]}