{"title":"The African Queen","artist":"Horace Silver","style":"Latin","key":"C-","chartData":[{"barData":["C-9","","Db9",""],"denominator":4,"numerator":4,"endBarline":"|","section":"A","startBarline":"["},{"barData":["C-9","","Db9",""],"endBarline":"|","startBarline":"|"},{"barData":["C-9","","Db9",""],"endBarline":"|","section":"A","annotations":[],"startBarline":"|"},{"barData":["C-9","","Db9",""],"endBarline":"|","startBarline":"|"},{"barData":["C-9","","Db9",""],"endBarline":"|","startBarline":"|"},{"barData":["C-9","","Db9",""],"endBarline":"|","startBarline":"|"},{"barData":["C-9","","Db9",""],"endBarline":"|","annotations":[],"startBarline":"|"},{"barData":["C-9","","Db9",""],"endBarline":"|","startBarline":"|"},{"barData":["C-9","","Db9",""],"endBarline":"|","section":"A","startBarline":"]"},{"barData":["C-9","","Db9",""],"endBarline":"|","startBarline":"|"},{"barData":["C-9","","Db9",""],"endBarline":"|","section":"A","annotations":[],"startBarline":"|"},{"barData":["C-9","","Db9",""],"endBarline":"|","startBarline":"|"},{"barData":["C-9","","Db9",""],"endBarline":"|","startBarline":"|"},{"barData":["C-9","","Db9",""],"endBarline":"|","startBarline":"|"},{"barData":["C-9","","Db9",""],"endBarline":"|","annotations":[],"startBarline":"|"},{"barData":["C-9","","Db9",""],"endBarline":"|","startBarline":"|"},{"barData":["Bb7","","A7",""],"endBarline":"|","section":"B","startBarline":"]"},{"barData":["Ab7","","G7",""],"endBarline":"|","startBarline":"|"},{"barData":["C-9","","Db9",""],"endBarline":"|","startBarline":"|"},{"barData":["C-9","","Db9",""],"endBarline":"|","startBarline":"|"},{"barData":["C-9","","Db9",""],"endBarline":"|","startBarline":"|"},{"barData":["C-9","","Db9",""],"endBarline":"Z","startBarline":"|"}]}